[
  {
    "name": "com.oracle.truffle.trufflenode.GraalJSAccess",
    "fields": [
      { "name": "sharedBuffer" }
    ],
    "methods": [
      { "name": "arrayBufferByteLength" },
      { "name": "arrayBufferDetach" },
      { "name": "arrayBufferGetContents" },
      { "name": "arrayBufferNew" },
      { "name": "arrayBufferNewBackingStore" },
      { "name": "arrayBufferViewBuffer" },
      { "name": "arrayBufferViewByteLength" },
      { "name": "arrayBufferViewByteOffset" },
      { "name": "arrayBufferWasDetached" },
      { "name": "arrayLength" },
      { "name": "arrayNew" },
      { "name": "arrayNewFromElements" },
      { "name": "backingStoreRegisterCallback" },
      { "name": "bigInt64ArrayNew" },
      { "name": "bigIntInt64Value" },
      { "name": "bigIntNew" },
      { "name": "bigIntNewFromUnsigned" },
      { "name": "bigIntNewFromWords" },
      { "name": "bigIntToWordsArray" },
      { "name": "bigIntUint64Value" },
      { "name": "bigIntWordCount" },
      { "name": "bigUint64ArrayNew" },
      { "name": "booleanObjectNew" },
      { "name": "booleanObjectValueOf" },
      { "name": "clearWeak" },
      { "name": "contextGetEmbedderData" },
      { "name": "contextGetExtrasBindingObject" },
      { "name": "contextGetPointerInEmbedderData" },
      { "name": "contextGetSecurityToken" },
      { "name": "contextGlobal" },
      { "name": "contextIsCodeGenerationFromStringsAllowed" },
      { "name": "contextNew" },
      { "name": "contextSetEmbedderData" },
      { "name": "contextSetPointerInEmbedderData" },
      { "name": "contextSetPromiseHooks" },
      { "name": "contextSetSecurityToken" },
      { "name": "create" },
      { "name": "dataViewNew" },
      { "name": "dateNew" },
      { "name": "dateTimeConfigurationChangeNotification" },
      { "name": "dateValueOf" },
      { "name": "exceptionCreateMessage" },
      { "name": "exceptionError" },
      { "name": "exceptionRangeError" },
      { "name": "exceptionReferenceError" },
      { "name": "exceptionSyntaxError" },
      { "name": "exceptionTypeError" },
      { "name": "externalNew" },
      { "name": "findDynamicObjectFields" },
      { "name": "fixedArrayGet" },
      { "name": "fixedArrayLength" },
      { "name": "float32ArrayNew" },
      { "name": "float64ArrayNew" },
      { "name": "functionCall" },
      { "name": "functionCall0" },
      { "name": "functionCall1" },
      { "name": "functionCall2" },
      { "name": "functionCall3" },
      { "name": "functionCall4" },
      { "name": "functionCall5" },
      { "name": "functionCall6" },
      { "name": "functionCall7" },
      { "name": "functionCall8" },
      { "name": "functionCall9" },
      { "name": "functionGetName" },
      { "name": "functionGetScriptColumnNumber" },
      { "name": "functionGetScriptLineNumber" },
      { "name": "functionGetSourceSection" },
      { "name": "functionNewInstance" },
      { "name": "functionResourceName" },
      { "name": "functionSetName" },
      { "name": "functionTemplateGetFunction" },
      { "name": "functionTemplateHasInstance" },
      { "name": "functionTemplateInherit" },
      { "name": "functionTemplateInstanceTemplate" },
      { "name": "functionTemplateNew" },
      { "name": "functionTemplatePrototypeTemplate" },
      { "name": "functionTemplateReadOnlyPrototype" },
      { "name": "functionTemplateSetCallHandler" },
      { "name": "functionTemplateSetClassName" },
      { "name": "int16ArrayNew" },
      { "name": "int32ArrayNew" },
      { "name": "int8ArrayNew" },
      { "name": "integerNew" },
      { "name": "isolateCancelTerminateExecution" },
      { "name": "isolateDispose" },
      { "name": "isolateEnableImportMetaInitializer" },
      { "name": "isolateEnableImportModuleDynamically" },
      { "name": "isolateEnablePrepareStackTraceCallback" },
      { "name": "isolateEnablePromiseHook" },
      { "name": "isolateEnablePromiseRejectCallback" },
      { "name": "isolateEnqueueMicrotask" },
      { "name": "isolateEnter" },
      { "name": "isolateEnterPolyglotEngine" },
      { "name": "isolateExecuteRunnable" },
      { "name": "isolateExit" },
      { "name": "isolateGetDoublePlaceholder" },
      { "name": "isolateGetHeapStatistics" },
      { "name": "isolateGetIntPlaceholder" },
      { "name": "isolateGetSafeIntPlaceholder" },
      { "name": "isolateInternalErrorCheck" },
      { "name": "isolateIsExecutionTerminating" },
      { "name": "isolateMeasureMemory" },
      { "name": "isolatePerformGC" },
      { "name": "isolateRequestInterrupt" },
      { "name": "isolateRunMicrotasks" },
      { "name": "isolateSchedulePauseOnNextStatement" },
      { "name": "isolateSetTaskRunner" },
      { "name": "isolateTerminateExecution" },
      { "name": "isolateThrowException" },
      { "name": "isolateThrowStackOverflowError" },
      { "name": "jsonParse" },
      { "name": "jsonStringify" },
      { "name": "makeWeak" },
      { "name": "mapNew" },
      { "name": "mapSet" },
      { "name": "messageGet" },
      { "name": "messageGetEndPosition" },
      { "name": "messageGetLineNumber" },
      { "name": "messageGetScriptResourceName" },
      { "name": "messageGetSourceLine" },
      { "name": "messageGetStackTrace" },
      { "name": "messageGetStartColumn" },
      { "name": "messageGetStartPosition" },
      { "name": "moduleCompile" },
      { "name": "moduleCreateSyntheticModule" },
      { "name": "moduleEvaluate" },
      { "name": "moduleInstantiate" },
      { "name": "moduleGetException" },
      { "name": "moduleGetIdentityHash" },
      { "name": "moduleGetModuleRequests" },
      { "name": "moduleGetNamespace" },
      { "name": "moduleGetStatus" },
      { "name": "moduleGetUnboundModuleScript" },
      { "name": "moduleIsGraphAsync" },
      { "name": "moduleRequestGetImportAssertions" },
      { "name": "moduleRequestGetSpecifier" },
      { "name": "moduleSetSyntheticModuleExport" },
      { "name": "nullInstance" },
      { "name": "numberNew" },
      { "name": "numberObjectNew" },
      { "name": "objectClone" },
      { "name": "objectCreateDataProperty" },
      { "name": "objectCreationContext" },
      { "name": "objectDefineProperty" },
      { "name": "objectDelete" },
      { "name": "objectDeletePrivate" },
      { "name": "objectForceSet" },
      { "name": "objectGet" },
      { "name": "objectGetConstructorName" },
      { "name": "objectGetIndex" },
      { "name": "objectGetOwnPropertyDescriptor" },
      { "name": "objectGetOwnPropertyNames" },
      { "name": "objectGetPrivate" },
      { "name": "objectGetPropertyNames" },
      { "name": "objectGetPrototype" },
      { "name": "objectGetRealNamedProperty" },
      { "name": "objectGetRealNamedPropertyAttributes" },
      { "name": "objectHas" },
      { "name": "objectHasOwnProperty" },
      { "name": "objectHasPrivate" },
      { "name": "objectHasRealNamedProperty" },
      { "name": "objectInternalFieldCount" },
      { "name": "objectIsConstructor" },
      { "name": "objectNew" },
      { "name": "objectPreviewEntries" },
      { "name": "objectSet" },
      { "name": "objectSetAccessor" },
      { "name": "objectSetAlignedPointerInInternalField" },
      { "name": "objectSetIndex" },
      { "name": "objectSetIntegrityLevel" },
      { "name": "objectSetInternalField" },
      { "name": "objectSetPrivate" },
      { "name": "objectSetPrototype" },
      { "name": "objectSlowGetAlignedPointerFromInternalField" },
      { "name": "objectSlowGetInternalField" },
      { "name": "objectTemplateNew" },
      { "name": "objectTemplateNewInstance" },
      { "name": "objectTemplateSetAccessor" },
      { "name": "objectTemplateSetCallAsFunctionHandler" },
      { "name": "objectTemplateSetHandler" },
      { "name": "objectTemplateSetInternalFieldCount" },
      { "name": "promiseResolverNew" },
      { "name": "promiseResolverReject" },
      { "name": "promiseResolverResolve" },
      { "name": "promiseResult" },
      { "name": "promiseState" },
      { "name": "proxyGetHandler" },
      { "name": "proxyGetTarget" },
      { "name": "proxyIsFunction" },
      { "name": "regexpGetFlags" },
      { "name": "regexpGetSource" },
      { "name": "regexpNew" },
      { "name": "scriptCompile" },
      { "name": "scriptCompilerCompileFunctionInContext" },
      { "name": "scriptGetUnboundScript" },
      { "name": "scriptOrModuleGetHostDefinedOptions" },
      { "name": "scriptOrModuleGetResourceName" },
      { "name": "scriptRun" },
      { "name": "setAdd" },
      { "name": "setNew" },
      { "name": "sharedArrayBufferByteLength" },
      { "name": "sharedArrayBufferExternalize" },
      { "name": "sharedArrayBufferGetContents" },
      { "name": "sharedArrayBufferNew" },
      { "name": "stackFrameGetColumn" },
      { "name": "stackFrameGetFunctionName" },
      { "name": "stackFrameGetLineNumber" },
      { "name": "stackFrameGetScriptName" },
      { "name": "stackFrameIsEval" },
      { "name": "stackTraceCurrentStackTrace" },
      { "name": "stringConcat" },
      { "name": "stringContainsOnlyOneByte" },
      { "name": "stringEmpty" },
      { "name": "stringEquals" },
      { "name": "stringExternalResourceCallback" },
      { "name": "stringLength" },
      { "name": "stringNew" },
      { "name": "stringNewFromTwoByte" },
      { "name": "stringObjectNew" },
      { "name": "stringObjectValueOf" },
      { "name": "stringUTF8Length" },
      { "name": "stringUTF8Write" },
      { "name": "stringWrite" },
      { "name": "stringWriteOneByte" },
      { "name": "symbolFor" },
      { "name": "symbolForApi" },
      { "name": "symbolGetAsyncIterator" },
      { "name": "symbolGetHasInstance" },
      { "name": "symbolGetIsConcatSpreadable" },
      { "name": "symbolGetIterator" },
      { "name": "symbolGetMatch" },
      { "name": "symbolGetReplace" },
      { "name": "symbolGetSearch" },
      { "name": "symbolGetSplit" },
      { "name": "symbolGetToPrimitive" },
      { "name": "symbolGetToStringTag" },
      { "name": "symbolGetUnscopables" },
      { "name": "symbolName" },
      { "name": "symbolNew" },
      { "name": "symbolPrivateForApi" },
      { "name": "symbolPrivateNew" },
      { "name": "templateSet" },
      { "name": "templateSetAccessorProperty" },
      { "name": "tryCatchException" },
      { "name": "tryCatchHasTerminated" },
      { "name": "typedArrayLength" },
      { "name": "uint16ArrayNew" },
      { "name": "uint32ArrayNew" },
      { "name": "uint8ArrayNew" },
      { "name": "uint8ClampedArrayNew" },
      { "name": "unboundScriptBindToContext" },
      { "name": "unboundScriptCompile" },
      { "name": "unboundScriptGetContent" },
      { "name": "unboundScriptGetId" },
      { "name": "undefinedInstance" },
      { "name": "valueDeserializerGetWireFormatVersion" },
      { "name": "valueDeserializerNew" },
      { "name": "valueDeserializerReadDouble" },
      { "name": "valueDeserializerReadHeader" },
      { "name": "valueDeserializerReadUint32" },
      { "name": "valueDeserializerReadUint64" },
      { "name": "valueDeserializerReadValue" },
      { "name": "valueDeserializerReadRawBytes" },
      { "name": "valueDeserializerTransferArrayBuffer" },
      { "name": "valueDouble" },
      { "name": "valueEquals" },
      { "name": "valueExternal" },
      { "name": "valueFlatten" },
      { "name": "valueInt32Value" },
      { "name": "valueInstanceOf" },
      { "name": "valueIntegerValue" },
      { "name": "valueIsArgumentsObject" },
      { "name": "valueIsAsyncFunction" },
      { "name": "valueIsBigIntObject" },
      { "name": "valueIsBooleanObject" },
      { "name": "valueIsGeneratorFunction" },
      { "name": "valueIsGeneratorObject" },
      { "name": "valueIsMapIterator" },
      { "name": "valueIsModuleNamespaceObject" },
      { "name": "valueIsNativeError" },
      { "name": "valueIsNumberObject" },
      { "name": "valueIsSetIterator" },
      { "name": "valueIsSharedArrayBuffer" },
      { "name": "valueIsStringObject" },
      { "name": "valueIsSymbolObject" },
      { "name": "valueIsWasmMemoryObject" },
      { "name": "valueIsWeakMap" },
      { "name": "valueIsWeakSet" },
      { "name": "valueSerializerNew" },
      { "name": "valueSerializerRelease" },
      { "name": "valueSerializerSize" },
      { "name": "valueSerializerWriteHeader" },
      { "name": "valueSerializerWriteValue" },
      { "name": "valueSerializerWriteUint32" },
      { "name": "valueSerializerWriteUint64" },
      { "name": "valueSerializerWriteDouble" },
      { "name": "valueSerializerWriteRawBytes" },
      { "name": "valueSerializerSetTreatArrayBufferViewsAsHostObjects" },
      { "name": "valueSerializerTransferArrayBuffer" },
      { "name": "valueStrictEquals" },
      { "name": "valueToArrayIndex" },
      { "name": "valueToBoolean" },
      { "name": "valueToDetailString" },
      { "name": "valueToInt32" },
      { "name": "valueToInteger" },
      { "name": "valueToNumber" },
      { "name": "valueToObject" },
      { "name": "valueToString" },
      { "name": "valueToUint32" },
      { "name": "valueType" },
      { "name": "valueTypeOf" },
      { "name": "valueUint32Value" },
      { "name": "valueUnknown" },
      { "name": "wasmModuleObjectFromCompiledModule" },
      { "name": "wasmModuleObjectGetCompiledModule" }
    ]
  },
  {
    "name": "com.oracle.truffle.trufflenode.NativeAccess",
    "methods": [
      { "name": "deallocate" },
      { "name": "executeAccessorGetter" },
      { "name": "executeAccessorSetter" },
      { "name": "executeFunction" },
      { "name": "executeFunction0" },
      { "name": "executeFunction1" },
      { "name": "executeFunction2" },
      { "name": "executeFunction3" },
      { "name": "executeFunction4" },
      { "name": "executeFunction5" },
      { "name": "executeFunction6" },
      { "name": "executeInterruptCallback" },
      { "name": "executePrepareStackTraceCallback" },
      { "name": "executePropertyHandlerDefiner" },
      { "name": "executePropertyHandlerDeleter" },
      { "name": "executePropertyHandlerDescriptor" },
      { "name": "executePropertyHandlerEnumerator" },
      { "name": "executePropertyHandlerGetter" },
      { "name": "executePropertyHandlerQuery" },
      { "name": "executePropertyHandlerSetter" },
      { "name": "getCoreModuleBinarySnapshot" },
      { "name": "notifyGCCallbacks" },
      { "name": "polyglotEngineEntered" },
      { "name": "weakCallback" },
      { "name": "deleterCallback" },
      { "name": "notifyPromiseHook" },
      { "name": "notifyPromiseRejectionTracker" },
      { "name": "notifyImportMetaInitializer" },
      { "name": "executeResolveCallback" },
      { "name": "executeImportModuleDynamicallyCallback" },
      { "name": "writeHostObject" },
      { "name": "readHostObject" },
      { "name": "throwDataCloneError" },
      { "name": "getSharedArrayBufferFromId" },
      { "name": "getSharedArrayBufferId" },
      { "name": "syntheticModuleEvaluationSteps" },
      { "name": "getWasmModuleTransferId" },
      { "name": "getWasmModuleFromId" },
      { "name": "notifyWasmStreamingCallback" },
      { "name": "postWakeUpTask" },
      { "name": "postRunnableTask" }
    ]
  },
  {
    "name": "java.lang.Boolean",
    "fields": [
      { "name": "FALSE" },
      { "name": "TRUE" }
    ]
  },
  {
    "name": "java.lang.String"
  },
  {
    "name": "java.lang.Object"
  },
  {
    "name": "java.nio.DirectByteBuffer",
    "fields": [
      { "name": "cleaner" }
    ]
  },
  {
    "name": "java.nio.DirectByteBuffer$Deallocator",
    "fields": [
      { "name": "address" }
    ]
  },
  {
    "name": "jdk.internal.ref.Cleaner",
    "fields": [
      { "name": "thunk" }
    ]
  }
]
